restate/__init__.py
restate/backends/__init__.py
restate/backends/asyncify.py
restate/backends/base.py
restate/backends/cached.py
restate/backends/fs.py
restate/backends/hybrid.py
restate/backends/memory.py
restate/controllers/__init__.py
restate/controllers/async_controller.py
restate/controllers/base.py
restate/controllers/callback_store.py
restate/controllers/internal_types.py
restate/controllers/sync_controller.py
restate/controllers/tracker.py
restate/shared/caller.py
restate/shared/constants.py
restate/shared/sentinel.py
restate-0.11.6.dist-info/licenses/LICENSE
restate-0.11.6.dist-info/METADATA
restate-0.11.6.dist-info/WHEEL
restate-0.11.6.dist-info/top_level.txt
restate-0.11.6.dist-info/RECORD
