Metadata-Version: 2.4
Name: restate
Version: 0.11.6
Summary: Storage-agnostic, reactive state management for Python
Project-URL: Homepage, https://github.com/saltforge/restate
Requires-Python: >=3.9
License-File: LICENSE
Requires-Dist: aiofiles>=24.1.0
Requires-Dist: typing-extensions>=4.12.2
Dynamic: license-file
